[{"name":"优化","type":"rgb(44, 173, 177)","r":24.42,"x":40,"y":-76.99},{"name":"入住","type":"rgb(23, 66, 121)","r":23.43,"x":24,"y":-30.55},{"name":"改进","type":"rgb(252, 196, 38)","r":23.2,"x":48,"y":-85},{"name":"执行","type":"rgb(44, 173, 177)","r":21.64,"x":37.33,"y":9.98},{"name":"伤害","type":"rgb(44, 173, 177)","r":21.33,"x":-80,"y":-79.36},{"name":"轻松","type":"rgb(252, 196, 38)","r":20.65,"x":58.67,"y":17.33},{"name":"受伤","type":"rgb(44, 173, 177)","r":20.28,"x":-64,"y":-22.46},{"name":"喜欢","type":"rgb(44, 173, 177)","r":20.28,"x":53.33,"y":5.67},{"name":"歧视","type":"rgb(252, 196, 38)","r":19.88,"x":-66.67,"y":-85},{"name":"签署","type":"rgb(44, 173, 177)","r":19.88,"x":37.33,"y":3.84},{"name":"便利","type":"rgb(252, 196, 38)","r":19.44,"x":64,"y":9.26},{"name":"创新","type":"rgb(44, 173, 177)","r":19.44,"x":74.67,"y":25.5},{"name":"妥协","type":"rgb(252, 196, 38)","r":18.97,"x":-40,"y":-85},{"name":"借鉴","type":"rgb(252, 196, 38)","r":18.97,"x":24,"y":-85},{"name":"违约","type":"rgb(252, 196, 38)","r":18.97,"x":-61.33,"y":-85},{"name":"共享","type":"rgb(252, 196, 38)","r":18.45,"x":53.33,"y":-19.85},{"name":"成功","type":"rgb(44, 173, 177)","r":18.45,"x":77.33,"y":-21.14},{"name":"观察","type":"rgb(249, 79, 133)","r":17.88,"x":13.33,"y":4.61},{"name":"中标","type":"rgb(44, 173, 177)","r":17.88,"x":32,"y":-50.58},{"name":"离开","type":"rgb(44, 173, 177)","r":17.24,"x":-24,"y":4.02},{"name":"淘汰","type":"rgb(44, 173, 177)","r":17.24,"x":-42.67,"y":-54.4},{"name":"看好","type":"rgb(44, 173, 177)","r":17.24,"x":58.67,"y":0},{"name":"招聘","type":"rgb(44, 173, 177)","r":16.52,"x":29.33,"y":-18.91},{"name":"倒闭","type":"rgb(44, 173, 177)","r":16.52,"x":-66.67,"y":-9.71},{"name":"累","type":"rgb(252, 196, 38)","r":16.52,"x":-29.33,"y":-13.27},{"name":"不利","type":"rgb(252, 196, 38)","r":16.52,"x":-50.67,"y":-85},{"name":"优美","type":"rgb(252, 196, 38)","r":15.68,"x":50.67,"y":-12.68},{"name":"食宿","type":"rgb(252, 196, 38)","r":14.69,"x":29.33,"y":-69.36},{"name":"领军","type":"rgb(249, 79, 133)","r":14.69,"x":72,"y":-2.42},{"name":"聚焦","type":"rgb(249, 79, 133)","r":14.69,"x":24,"y":-5.8},{"name":"难受","type":"rgb(44, 173, 177)","r":13.48,"x":-37.33,"y":17},{"name":"激励","type":"rgb(44, 173, 177)","r":13.48,"x":58.67,"y":-27.4},{"name":"友好","type":"rgb(252, 196, 38)","r":13.48,"x":61.33,"y":8.77},{"name":"运营","type":"rgb(23, 66, 121)","r":13.48,"x":42.67,"y":-15.35},{"name":"正规","type":"rgb(44, 173, 177)","r":11.92,"x":50.67,"y":-4.04}]